{
    "tiles": [
        "https://samplemaps.ankapong.com/data/main/{z}/{x}/{y}.pbf"
    ],
    "name": "pn_bt_longduong.mbtiles + pn_bt_logioi.mbtiles + pn_bt_landuse.mbtiles + pn_bt_constructions.mbtiles + pn_bt_parcels.mbtiles + tanphu.mbtiles + tb.mbtiles + quan8.mbtiles + binhthanh.mbtiles + addresses.mbtiles + parcels.mbtiles + constructions.mbtiles",
    "format": "pbf",
    "basename": "main.mbtiles",
    "id": "main",
    "description": "landuse.mbtiles",
    "version": "2",
    "minzoom": 12,
    "maxzoom": 20,
    "center": [
        106.738873,
        10.782552,
        20
    ],
    "bounds": [
        101.290169,
        0.01236,
        112.976875,
        21.404491
    ],
    "type": "overlay",
    "generator": "tile-join v1.36.0",
    "generator_options": "tippecanoe -f -o pn_bt_longduong.mbtiles -l longduong --no-feature-limit --no-tile-size-limit '--minimum-zoom=15' '--maximum-zoom=20' pn_bt_longduong.json; tippecanoe -f -o pn_bt_logioi.mbtiles -l logioi --no-feature-limit --no-tile-size-limit '--minimum-zoom=17' '--maximum-zoom=20' pn_bt_logioi.json; tippecanoe -f -o pn_bt_landuse.mbtiles -l landuse '--minimum-zoom=12' '--maximum-zoom=20' --no-feature-limit --no-tile-size-limit pn_bt_landuse.json; tippecanoe -f -o pn_bt_constructions.mbtiles -l constructions '--minimum-zoom=19' '--maximum-zoom=20' pn_bt_constructions.json; tippecanoe -f -o pn_bt_parcels.mbtiles -l parcels --no-clipping --no-feature-limit --no-tile-size-limit '--minimum-zoom=17' '--maximum-zoom=20' pn_bt_parcels.json; tippecanoe -f -o tanphu.mbtiles -l addresses --no-feature-limit --no-tile-size-limit '--minimum-zoom=18' '--maximum-zoom=20' tanphu.json; tippecanoe -f -o tb.mbtiles -l addresses --no-feature-limit --no-tile-size-limit '--minimum-zoom=18' '--maximum-zoom=20' addresses.json; tippecanoe -f -o quan8.mbtiles -l addresses --no-feature-limit --no-tile-size-limit '--minimum-zoom=18' '--maximum-zoom=20' quan8.json; tippecanoe -f -o binhthanh.mbtiles -l addresses --no-feature-limit --no-tile-size-limit '--minimum-zoom=18' '--maximum-zoom=20' binhthanh.json; tippecanoe -f -o addresses.mbtiles -l addresses --no-feature-limit --no-tile-size-limit '--minimum-zoom=18' '--maximum-zoom=20' addresses.json; tile-join -f -o addresses.mbtiles other.mbtiles tb.mbtiles quan8.mbtiles tanphu.mbtiles binhthanh.mbtiles; tippecanoe -f -o parcels.mbtiles -l parcels --no-clipping --no-feature-limit --no-tile-size-limit '--minimum-zoom=17' '--maximum-zoom=20' parcels.json; tippecanoe -f -o constructions.mbtiles -l constructions '--minimum-zoom=19' '--maximum-zoom=20' constructions.json; tippecanoe -f -o longduong.mbtiles -l longduong --no-feature-limit --no-tile-size-limit '--minimum-zoom=15' '--maximum-zoom=20' longduong.json; tippecanoe -f -o logioi.mbtiles -l logioi --no-feature-limit --no-tile-size-limit '--minimum-zoom=17' '--maximum-zoom=20' logioi.json; tippecanoe -f -o landuse.mbtiles -l landuse '--minimum-zoom=12' '--maximum-zoom=20' --no-feature-limit --no-tile-size-limit landuse.json; tile-join -f -o main.mbtiles parcels.mbtiles constructions.mbtiles logioi.mbtiles longduong.mbtiles landuse.mbtiles addresses.mbtiles pn_bt_parcels.mbtiles pn_bt_constructions.mbtiles pn_bt_logioi.mbtiles pn_bt_longduong.mbtiles pn_bt_landuse.mbtiles",
    "vector_layers": [
        {
            "id": "addresses",
            "description": "",
            "minzoom": 18,
            "maxzoom": 20,
            "fields": {
                "housenumber": "String"
            }
        },
        {
            "id": "constructions",
            "description": "",
            "minzoom": 19,
            "maxzoom": 20,
            "fields": {}
        },
        {
            "id": "landuse",
            "description": "",
            "minzoom": 12,
            "maxzoom": 20,
            "fields": {
                "landuse": "String"
            }
        },
        {
            "id": "logioi",
            "description": "",
            "minzoom": 17,
            "maxzoom": 20,
            "fields": {
                "class": "String"
            }
        },
        {
            "id": "longduong",
            "description": "",
            "minzoom": 15,
            "maxzoom": 20,
            "fields": {}
        },
        {
            "id": "parcels",
            "description": "",
            "minzoom": 17,
            "maxzoom": 20,
            "fields": {
                "id": "Number"
            }
        }
    ],
    "tilestats": {
        "layerCount": 6,
        "layers": [
            {
                "layer": "addresses",
                "count": 680798,
                "geometry": "Point",
                "attributeCount": 1,
                "attributes": [
                    {
                        "attribute": "housenumber",
                        "count": 1000,
                        "type": "string",
                        "values": [
                            " ",
                            "           108/105",
                            "     73/18",
                            "    221/ 9",
                            "   221/ 11",
                            "   221/ 13",
                            "   25 A Cao Bá Nhạ Tổ 45 ",
                            "   379 Bến Chương Dương",
                            "   383 Bến Chương Dương   ",
                            "   71/",
                            "   S©n Chung ",
                            "  168/75 Nguyễn Cư Trinh Tổ 69",
                            "  168/75/10 NguyÔn C­ Trinh Tæ 70",
                            "  168/75/2 NguyÔn C­ Trinh Tæ 70",
                            "  168/75/4 NguyÔn C­ Trinh Tæ 70",
                            "  168/75/6 NguyÔn C­ Trinh Tæ 70",
                            "  168/75/8 NguyÔn C­ Trinh Tæ 70",
                            "  168/77 Nguyễn Cư Trinh Tổ 69",
                            "  168/79 Nguyễn Cư Trinh Tổ 69",
                            "  168/81 Nguyễn Cư Trinh Tổ 69",
                            "  168/81A Nguyễn Cư Trinh Tổ 69",
                            "  168/83 Nguyễn Cư Trinh Tổ 69",
                            "  24 / 25 A  Cao Bá Nhạ Tổ 45 ",
                            "  24 /28 D  Cao Bá Nhạ Tổ 45 ",
                            "  24 D  Cao Bá Nhạ Tổ 45 ",
                            "  24/ 60 Nguyễn Văn Cừ",
                            "  24/ 66 Nguyễn Văn Cừ ",
                            "  24/ 68 Nguyễn Văn Cừ",
                            "  24/ 70 Nguyễn Văn Cừ ",
                            "  25 B  Cao Bá Nhạ Tổ 45 ",
                            "  25 C  Cao Bá Nhạ Tổ 45 ",
                            "  28 / 24   Cao Bá Nhạ Tổ 45 ",
                            "  28 / 24 F  Cao Bá Nhạ Tổ 45 ",
                            "  28 /24E  Cao Bá Nhạ Tổ 45 ",
                            "  28 /28 B  Cao Bá Nhạ Tổ 45 ",
                            "  354 Bến Chương Dương",
                            "  7/7A ",
                            "  TK15/8 Nguyễn Cảnh Chân ",
                            "  TK18/ 18 Nguyễn Cảnh Chân ",
                            "  TK36/ 18 Nguyễn Cảnh Chân ",
                            "  TK49/ 10 Bến Chương Dương ",
                            " /1/12",
                            " /10/15",
                            " /10/2",
                            " /10/6",
                            " /10A",
                            " /12",
                            " /12/13",
                            " /12A",
                            " /13/2",
                            " /14",
                            " /14/1A",
                            " /14/3",
                            " /15/10",
                            " /15/11",
                            " /15/11A",
                            " /15/14",
                            " /15/15",
                            " /15/17",
                            " /15/19",
                            " /15/19A",
                            " /15/19A1",
                            " /15/2",
                            " /15/6",
                            " /15/8",
                            " /16",
                            " /16/10",
                            " /16/15",
                            " /16/17",
                            " /16/21",
                            " /16/23",
                            " /16/23A",
                            " /16/23B",
                            " /16/26A",
                            " /16/27",
                            " /16/6",
                            " /16/6A",
                            " /16/6B",
                            " /16/7",
                            " /16/8",
                            " /16A",
                            " /18",
                            " /18/11",
                            " /18/3",
                            " /18/4",
                            " /18/6",
                            " /2/1",
                            " /2/21F",
                            " /2/21G",
                            " /2/26",
                            " /2/27",
                            " /2/31",
                            " /2/34",
                            " /2/36",
                            " /2/36A",
                            " /21",
                            " /23/1",
                            " /23/10",
                            " /23/2",
                            " /23/3"
                        ]
                    }
                ]
            },
            {
                "layer": "constructions",
                "count": 4234719,
                "geometry": "LineString",
                "attributeCount": 0,
                "attributes": []
            },
            {
                "layer": "landuse",
                "count": 625024,
                "geometry": "Polygon",
                "attributeCount": 1,
                "attributes": [
                    {
                        "attribute": "landuse",
                        "count": 20,
                        "type": "string",
                        "values": [
                            "commer",
                            "coquan",
                            "culture",
                            "edu",
                            "green",
                            "honhop",
                            "hotel",
                            "industry",
                            "kythuat",
                            "medic",
                            "metro",
                            "military",
                            "nghiatrang",
                            "nuoc",
                            "podium",
                            "public",
                            "resident",
                            "sidewalk",
                            "sport",
                            "tongiao"
                        ]
                    }
                ]
            },
            {
                "layer": "logioi",
                "count": 828534,
                "geometry": "LineString",
                "attributeCount": 1,
                "attributes": [
                    {
                        "attribute": "class",
                        "count": 2,
                        "type": "string",
                        "values": [
                            "junior",
                            "senior"
                        ]
                    }
                ]
            },
            {
                "layer": "longduong",
                "count": 688859,
                "geometry": "LineString",
                "attributeCount": 0,
                "attributes": []
            },
            {
                "layer": "parcels",
                "count": 4924768,
                "geometry": "Polygon",
                "attributeCount": 1,
                "attributes": [
                    {
                        "attribute": "id",
                        "count": 1000,
                        "type": "number",
                        "values": [
                            0,
                            1,
                            10,
                            100,
                            1000,
                            10000,
                            100000,
                            100001,
                            100002,
                            100003,
                            100004,
                            100005,
                            100006,
                            100007,
                            100008,
                            100009,
                            10001,
                            100010,
                            100011,
                            100012,
                            100013,
                            100014,
                            100015,
                            100016,
                            100017,
                            100018,
                            100019,
                            10002,
                            100020,
                            100021,
                            100022,
                            100023,
                            100024,
                            100025,
                            100026,
                            100027,
                            100028,
                            100029,
                            10003,
                            100030,
                            100031,
                            100032,
                            100033,
                            100034,
                            100035,
                            100036,
                            100037,
                            100038,
                            100039,
                            10004,
                            100040,
                            100041,
                            100042,
                            100043,
                            100044,
                            100045,
                            100046,
                            100047,
                            100048,
                            100049,
                            10005,
                            100050,
                            100051,
                            100052,
                            100053,
                            100054,
                            100055,
                            100056,
                            100057,
                            100058,
                            100059,
                            10006,
                            100060,
                            100061,
                            100062,
                            100063,
                            100064,
                            100065,
                            100066,
                            100067,
                            100068,
                            100069,
                            10007,
                            100070,
                            100071,
                            100072,
                            100073,
                            100074,
                            100075,
                            100076,
                            100077,
                            100078,
                            100079,
                            10008,
                            100080,
                            100081,
                            100082,
                            100083,
                            100084,
                            100085
                        ],
                        "min": 0,
                        "max": 689241
                    }
                ]
            }
        ]
    },
    "tilejson": "2.0.0"
}